chess_dataset/__init__.py
chess_dataset-0.1.0.dist-info/METADATA
chess_dataset-0.1.0.dist-info/WHEEL
chess_dataset-0.1.0.dist-info/top_level.txt
chess_dataset-0.1.0.dist-info/RECORD
