Metadata-Version: 2.1
Name: chess-dataset
Version: 0.1.0
Summary: Chess dataset for OCR+decoding
Author-email: Marcel Claramunt <marcel@moveread.com>
Project-URL: repo, https://github.com/moveread/REPO.git
Requires-Python: >=3.10
